{
    "ArticleID": "20260402055650740",
    "URL": "https://dantri.com.vn/kinh-doanh/vi-sao-gia-vang-roi-manh-xong-lai-bat-tang-len-sat-4800-usdounce-20260402055650740.htm",
    "Slug": "vi-sao-gia-vang-roi-manh-xong-lai-bat-tang-len-sat-4800-usdounce",
    "Source": "Dân Trí",
    "Title": "Vì sao giá vàng rơi mạnh xong lại bật tăng lên sát 4.800 USD/ounce?",
    "BriefDescription": "Theo Bloomberg, giá vàng vừa ghi nhận chuỗi tăng giá 4 phiên liên tiếp. Trên thị trường giao ngay, kim loại quý có thời điểm lên sát mốc 4.800 USD/ounce trước khi thu hẹp đà tăng. Động lực chính hỗ trợ đà phục hồi này đến từ việc USD suy yếu, giúp vàng trở nên \"rẻ\" và hấp dẫn hơn.",
    "Category": "Kinh doanh",
    "NewsType": "Tài chính",
    "ArticleFormat": "Phân tích",
    "Tags": [
        "giá vàng hôm nay",
        "đầu tư vàng",
        "dự báo giá vàng",
        "Lãi suất Fed",
        "xung đột Trung Đông"
    ],
    "DateOfPublication": "2026-04-02 05:56",
    "SourceInformation": [
        "Bloomberg",
        "Economic Times",
        "Suki Cooper (Financial Times)",
        "The Motley Fool"
    ],
    "ContentSummary": "Bài viết phân tích sâu về sự biến động của giá vàng, giải thích nguyên nhân giá vàng rơi mạnh (chốt lời, nhu cầu thanh khoản) và bật tăng trở lại (USD suy yếu, kỳ vọng cắt giảm lãi suất Fed, hạ nhiệt địa chính trị). Đồng thời, bài báo cũng thảo luận về triển vọng của vàng và bạc, các yếu tố ảnh hưởng như lãi suất, lạm phát, địa chính trị, và đưa ra lời khuyên cho nhà đầu tư."
}